breadboard/__init__.py
breadboard/auth.py
breadboard/client.py
breadboard/mixins/ImageMixins.py
breadboard/mixins/RunMixins.py
breadboard/mixins/__init__.py
breadboard-1.1.7.dist-info/METADATA
breadboard-1.1.7.dist-info/RECORD
breadboard-1.1.7.dist-info/WHEEL
breadboard-1.1.7.dist-info/top_level.txt
