Metadata-Version: 2.1
Name: breadboard
Version: 1.1.7
Summary: Python API client for the Breadboard API in the Zwierlein labs
Home-page: https://github.com/biswaroopmukherjee/breadboard-python-client
Author: Biswaroop Mukherjee
Author-email: mail.biswaroop@gmail.com
License: MIT license
Platform: UNKNOWN
